an_cudachecker/__init__.py
an_cudachecker/cudachecker.py
an_cudachecker-0.1.1.dist-info/LICENSE
an_cudachecker-0.1.1.dist-info/METADATA
an_cudachecker-0.1.1.dist-info/WHEEL
an_cudachecker-0.1.1.dist-info/top_level.txt
an_cudachecker-0.1.1.dist-info/RECORD
