Metadata-Version: 2.2
Name: an_cudachecker
Version: 0.1.1
Summary: A package for an_cudachecker.
Home-page: https://github.com/Atsushi888/Atsushi888
Author: Atsushi888
Author-email: Atsushi888 <vtgrotxu@gmail.com>
License: MIT License
Project-URL: Homepage, https://github.com/Atsushi888/an_cudachecker
Project-URL: Repository, https://github.com/Atsushi888/an_cudachecker
Requires-Python: >=3.6
License-File: LICENSE
Dynamic: author
Dynamic: home-page
Dynamic: requires-python
